eightBitCounter/eightBitCounter.vhd
LIBRARY IEEE;
USE IEEE.STD_LOGIC_1164.ALL;
USE IEEE.NUMERIC_STD.ALL;

ENTITY eightBitCounter IS
    GENERIC (
        WIDTH : INTEGER := 7
    );
    PORT (
        clk : IN STD_LOGIC;
        clear : IN STD_LOGIC;
        count : OUT STD_LOGIC_VECTOR (WIDTH DOWNTO 0)
    );
END eightBitCounter;

ARCHITECTURE Behavioral OF eightBitCounter IS
    SIGNAL counter : unsigned(WIDTH DOWNTO 0) := (OTHERS => '0');
BEGIN
    PROCESS (clk, clear)
    BEGIN
        IF clear = '1' THEN
            counter <= (OTHERS => '0');
        ELSIF rising_edge(clk) THEN
            counter <= counter + 1;
        END IF;
    END PROCESS;

    count <= STD_LOGIC_VECTOR(counter);
END Behavioral;

eightBitCounter/tb_eightBitCounter.vhd
LIBRARY IEEE;
USE IEEE.STD_LOGIC_1164.ALL;
USE IEEE.NUMERIC_STD.ALL;

ENTITY tb_eightBitCounter IS
END tb_eightBitCounter;

ARCHITECTURE behavior OF tb_eightBitCounter IS
    -- Component Declaration for the Unit Under Test (UUT)
    COMPONENT eightBitCounter
        GENERIC (
            WIDTH : INTEGER := 4
        );
        PORT (
            clk : IN STD_LOGIC;
            clear : IN STD_LOGIC;
            count : OUT STD_LOGIC_VECTOR(WIDTH DOWNTO 0)
        );
    END COMPONENT;

    -- Signals for the UUT
    SIGNAL clk : STD_LOGIC := '0';
    SIGNAL clear : STD_LOGIC := '0';
    SIGNAL count : STD_LOGIC_VECTOR(4 DOWNTO 0);

    -- Clock period definition
    CONSTANT clk_period : TIME := 10 ns;

BEGIN
    -- Instantiate the Unit Under Test (UUT)
    uut: eightBitCounter
        GENERIC MAP (
            WIDTH => 4
        )
        PORT MAP (
            clk => clk,
            clear => clear,
            count => count
        );

    -- Clock process definitions
    clk_process : PROCESS
        VARIABLE counter : INTEGER := 0;
    BEGIN
        WHILE counter < 42 LOOP
            clear <= '0';
            if(counter = 4 or counter = 8) then
                clear <= '1';
            end if;
            
            clk <= '0';
            WAIT FOR clk_period/2;
            clk <= '1';
            WAIT FOR clk_period/2;
            counter := counter + 1;
        END LOOP;
        WAIT; -- Wait indefinitely after the loop
    END PROCESS;

END behavior;

tb_eightBitCounter.vcd
$date
  Fri Nov  8 17:31:27 2024
$end
$version
  GHDL v0
$end
$timescale
  1 fs
$end
$scope module standard $end
$upscope $end
$scope module std_logic_1164 $end
$upscope $end
$scope module numeric_std $end
$upscope $end
$scope module tb_eightbitcounter $end
$var reg 1 ! clk $end
$var reg 1 " clear $end
$var reg 5 # count[4:0] $end
$scope module uut $end
$var reg 1 $ clk $end
$var reg 1 % clear $end
$var reg 5 & count[4:0] $end
$var reg 5 ' counter[4:0] $end
$upscope $end
$upscope $end
$enddefinitions $end
#0
0!
0"
b00000 #
0$
0%
b00000 &
b00000 '
#5000000
1!
b00001 #
1$
b00001 &
b00001 '
#10000000
0!
0$
#15000000
1!
b00010 #
1$
b00010 &
b00010 '
#20000000
0!
0$
#25000000
1!
b00011 #
1$
b00011 &
b00011 '
#30000000
0!
0$
#35000000
1!
b00100 #
1$
b00100 &
b00100 '
#40000000
0!
1"
b00000 #
0$
1%
b00000 &
b00000 '
#45000000
1!
1$
#50000000
0!
0"
0$
0%
#55000000
1!
b00001 #
1$
b00001 &
b00001 '
#60000000
0!
0$
#65000000
1!
b00010 #
1$
b00010 &
b00010 '
#70000000
0!
0$
#75000000
1!
b00011 #
1$
b00011 &
b00011 '
#80000000
0!
1"
b00000 #
0$
1%
b00000 &
b00000 '
#85000000
1!
1$
#90000000
0!
0"
0$
0%
#95000000
1!
b00001 #
1$
b00001 &
b00001 '
#100000000
0!
0$
#105000000
1!
b00010 #
1$
b00010 &
b00010 '
#110000000
0!
0$
#115000000
1!
b00011 #
1$
b00011 &
b00011 '
#120000000
0!
0$
#125000000
1!
b00100 #
1$
b00100 &
b00100 '
#130000000
0!
0$
#135000000
1!
b00101 #
1$
b00101 &
b00101 '
#140000000
0!
0$
#145000000
1!
b00110 #
1$
b00110 &
b00110 '
#150000000
0!
0$
#155000000
1!
b00111 #
1$
b00111 &
b00111 '
#160000000
0!
0$
#165000000
1!
b01000 #
1$
b01000 &
b01000 '
#170000000
0!
0$
#175000000
1!
b01001 #
1$
b01001 &
b01001 '
#180000000
0!
0$
#185000000
1!
b01010 #
1$
b01010 &
b01010 '
#190000000
0!
0$
#195000000
1!
b01011 #
1$
b01011 &
b01011 '
#200000000
0!
0$
#205000000
1!
b01100 #
1$
b01100 &
b01100 '
#210000000
0!
0$
#215000000
1!
b01101 #
1$
b01101 &
b01101 '
#220000000
0!
0$
#225000000
1!
b01110 #
1$
b01110 &
b01110 '
#230000000
0!
0$
#235000000
1!
b01111 #
1$
b01111 &
b01111 '
#240000000
0!
0$
#245000000
1!
b10000 #
1$
b10000 &
b10000 '
#250000000
0!
0$
#255000000
1!
b10001 #
1$
b10001 &
b10001 '
#260000000
0!
0$
#265000000
1!
b10010 #
1$
b10010 &
b10010 '
#270000000
0!
0$
#275000000
1!
b10011 #
1$
b10011 &
b10011 '
#280000000
0!
0$
#285000000
1!
b10100 #
1$
b10100 &
b10100 '
#290000000
0!
0$
#295000000
1!
b10101 #
1$
b10101 &
b10101 '
#300000000
0!
0$
#305000000
1!
b10110 #
1$
b10110 &
b10110 '
#310000000
0!
0$
#315000000
1!
b10111 #
1$
b10111 &
b10111 '
#320000000
0!
0$
#325000000
1!
b11000 #
1$
b11000 &
b11000 '
#330000000
0!
0$
#335000000
1!
b11001 #
1$
b11001 &
b11001 '
#340000000
0!
0$
#345000000
1!
b11010 #
1$
b11010 &
b11010 '
#350000000
0!
0$
#355000000
1!
b11011 #
1$
b11011 &
b11011 '
#360000000
0!
0$
#365000000
1!
b11100 #
1$
b11100 &
b11100 '
#370000000
0!
0$
#375000000
1!
b11101 #
1$
b11101 &
b11101 '
#380000000
0!
0$
#385000000
1!
b11110 #
1$
b11110 &
b11110 '
#390000000
0!
0$
#395000000
1!
b11111 #
1$
b11111 &
b11111 '
#400000000
0!
0$
#405000000
1!
b00000 #
1$
b00000 &
b00000 '
#410000000
0!
0$
#415000000
1!
b00001 #
1$
b00001 &
b00001 '
