shared/syncRegister.vhd
LIBRARY IEEE;
USE IEEE.STD_LOGIC_1164.ALL;

ENTITY syncRegister IS
    GENERIC (
        WIDTH : INTEGER := 7
    );
    PORT (
        clk : IN STD_LOGIC;
        reset : IN STD_LOGIC;
        d : IN STD_LOGIC_VECTOR(WIDTH DOWNTO 0);
        q : OUT STD_LOGIC_VECTOR(WIDTH DOWNTO 0)
    );
END syncRegister;

ARCHITECTURE Behavioral OF syncRegister IS
    SIGNAL reg : STD_LOGIC_VECTOR(WIDTH DOWNTO 0);
BEGIN
    PROCESS (clk, reset)
    BEGIN
        IF reset = '1' THEN
            reg <= (OTHERS => '0');
        ELSIF rising_edge(clk) THEN
            reg <= d;
        END IF;
    END PROCESS;

    q <= reg;
END Behavioral;

shared/mux2to1.vhd
library IEEE;
use IEEE.STD_LOGIC_1164.ALL;

entity mux2to1 is
    generic (
        WIDTH : integer := 1
    );
    port (
        A : in  STD_LOGIC_VECTOR(WIDTH downto 0);  -- Input A
        B : in  STD_LOGIC_VECTOR(WIDTH downto 0);  -- Input B
        Sel : in  STD_LOGIC;  -- Select input
        Y : out  STD_LOGIC_VECTOR(WIDTH downto 0)  -- Output
    );
end mux2to1;

architecture Behavioral of mux2to1 is
begin
    process(A, B, Sel)
    begin
        if Sel = '0' then
            Y <= A;
        else
            Y <= B;
        end if;
    end process;
end Behavioral;

syncSignalProcessing/syncSignalProcessing.vhd
LIBRARY IEEE;
USE IEEE.STD_LOGIC_1164.ALL;
USE IEEE.NUMERIC_STD.ALL;

ENTITY syncSignalProcessing IS
    GENERIC (
        IN_SIZE : INTEGER := 7;
        OUT_SIZE : INTEGER := 15
    );
    PORT (
        clk : IN STD_LOGIC;
        reset : IN STD_LOGIC;
        A : IN STD_LOGIC_VECTOR(IN_SIZE DOWNTO 0);
        B : IN STD_LOGIC_VECTOR(IN_SIZE DOWNTO 0);
        ACTIVATION : IN STD_LOGIC;
        OP : IN STD_LOGIC;
        S : OUT STD_LOGIC_VECTOR(OUT_SIZE DOWNTO 0)
    );
END syncSignalProcessing;
ARCHITECTURE Behavioral OF syncSignalProcessing IS
    -- Define the sum and mul signals with appropriate widths
    SIGNAL sum : unsigned(IN_SIZE DOWNTO 0);  -- 8 bits for the sum
    SIGNAL mul : unsigned(2 * (IN_SIZE + 1) - 1 DOWNTO 0);  -- 16 bits for the product (enough for 2 * (IN_SIZE + 1))

    SIGNAL OPOut : STD_LOGIC_VECTOR(OUT_SIZE DOWNTO 0);
    SIGNAL ACTIVATIONOut : STD_LOGIC_VECTOR(OUT_SIZE DOWNTO 0);
    SIGNAL zero_vector : STD_LOGIC_VECTOR(OUT_SIZE DOWNTO 0) := (OTHERS => '0');

    COMPONENT mux2to1 IS
        GENERIC (
            WIDTH : INTEGER := 1
        );
        PORT (
            A : IN STD_LOGIC_VECTOR(WIDTH DOWNTO 0);
            B : IN STD_LOGIC_VECTOR(WIDTH DOWNTO 0);
            Sel : IN STD_LOGIC;
            Y : OUT STD_LOGIC_VECTOR(WIDTH DOWNTO 0)
        );
    END COMPONENT;

    COMPONENT syncRegister IS
    GENERIC (
        WIDTH : INTEGER := 16
    );
    PORT (
        clk : IN STD_LOGIC;
        reset : IN STD_LOGIC;
        d : IN STD_LOGIC_VECTOR(WIDTH DOWNTO 0);
        q : OUT STD_LOGIC_VECTOR(WIDTH DOWNTO 0)
    );
END COMPONENT;

    -- Signals for resized sum and mul
    SIGNAL sum_resized : STD_LOGIC_VECTOR(OUT_SIZE DOWNTO 0);  -- resized sum
    SIGNAL mul_resized : STD_LOGIC_VECTOR(OUT_SIZE DOWNTO 0);  -- resized mul

BEGIN

    -- Process to compute sum and mul
    PROCESS (A, B, ACTIVATION, OP)
    BEGIN
        sum <= unsigned(A) + unsigned(B);  -- sum of A and B
        mul <= unsigned(A) * unsigned(B);  -- product of A and B
    END PROCESS;

    -- Resize sum and mul to match OUT_SIZE, ensuring correct bit width
    sum_resized <= std_logic_vector(resize(sum, OUT_SIZE + 1));  -- Convert to std_logic_vector and resize
    mul_resized <= std_logic_vector(resize(mul, OUT_SIZE + 1));  -- Convert to std_logic_vector and resize

    -- U1: First Mux, sum and mul are passed in and selected by OP
    U1 : mux2to1
    GENERIC MAP(
        WIDTH => OUT_SIZE
    )
    PORT MAP(
        A => sum_resized,  -- Use resized sum
        B => mul_resized,  -- Use resized mul
        Sel => OP,
        Y => OPOut
    );

    -- U2: Second Mux, passing zero_vector or OPOut to S
    U2 : mux2to1
    GENERIC MAP(
        WIDTH => OUT_SIZE
    )
    PORT MAP(
        A => zero_vector,
        B => OPOut,
        Sel => ACTIVATION,
        Y => ACTIVATIONOut  -- S now has the width of OUT_SIZE
    );

    U3: syncRegister
    GENERIC MAP(
        WIDTH => OUT_SIZE
    )
    PORT MAP(
        clk => clk,
        reset => reset,
        d => ACTIVATIONOut,
        q => S
    );

END Behavioral;

syncSignalProcessing/tb_syncSignalProcessing.vhd
LIBRARY IEEE;
USE IEEE.STD_LOGIC_1164.ALL;
USE IEEE.NUMERIC_STD.ALL;

ENTITY tb_syncSignalProcessing IS
END tb_syncSignalProcessing;

ARCHITECTURE behavior OF tb_syncSignalProcessing IS

    -- Component Declaration for the Unit Under Test (UUT)
    COMPONENT syncSignalProcessing
        GENERIC (
            IN_SIZE : INTEGER := 7;
            OUT_SIZE : INTEGER := 15
        );
        PORT (
            clk : IN STD_LOGIC;
            reset : IN STD_LOGIC;
            A : IN STD_LOGIC_VECTOR(IN_SIZE DOWNTO 0);
            B : IN STD_LOGIC_VECTOR(IN_SIZE DOWNTO 0);
            ACTIVATION : IN STD_LOGIC;
            OP : IN STD_LOGIC;
            S : OUT STD_LOGIC_VECTOR(OUT_SIZE DOWNTO 0)
        );
    END COMPONENT;

    -- Signals for the UUT
    SIGNAL clk : STD_LOGIC := '0';
    SIGNAL reset : STD_LOGIC := '0';
    SIGNAL A : STD_LOGIC_VECTOR(7 DOWNTO 0) := (OTHERS => '0');
    SIGNAL B : STD_LOGIC_VECTOR(7 DOWNTO 0) := (OTHERS => '0');
    SIGNAL ACTIVATION : STD_LOGIC := '0';
    SIGNAL OP : STD_LOGIC := '0';
    SIGNAL S : STD_LOGIC_VECTOR(15 DOWNTO 0);

    -- Clock period definition
    CONSTANT clk_period : TIME := 10 ns;

BEGIN

    -- Instantiate the Unit Under Test (UUT)
    uut : syncSignalProcessing
    GENERIC MAP(
        IN_SIZE => 7,
        OUT_SIZE => 15
    )
    PORT MAP(
        clk => clk,
        reset => reset,
        A => A,
        B => B,
        ACTIVATION => ACTIVATION,
        OP => OP,
        S => S
    );

    -- Clock process definitions
    clk_process : PROCESS
        VARIABLE counter : INTEGER := 0;
    BEGIN
        WHILE counter < 30 LOOP
            clk <= '0';
            WAIT FOR clk_period/2;
            clk <= '1';
            WAIT FOR clk_period/2;
            counter := counter + 1;
        END LOOP;
        WAIT; -- Wait indefinitely after the loop
    END PROCESS;

    -- Stimulus process
    stim_proc : PROCESS
    BEGIN
        -- Reset the system
        reset <= '1';
        WAIT FOR 20 ns;
        reset <= '0';
        WAIT FOR 20 ns;

        -- Test case 1: A + B, OP = '0', ACTIVATION = '0'
        A <= STD_LOGIC_VECTOR(to_unsigned(10, 8));
        B <= STD_LOGIC_VECTOR(to_unsigned(20, 8));
        OP <= '0';
        ACTIVATION <= '0';
        WAIT FOR 20 ns;
        -- Reset the system
        reset <= '1';
        WAIT FOR 20 ns;
        reset <= '0';
        WAIT FOR 20 ns;

        -- Test case 2: A * B, OP = '1', ACTIVATION = '0'
        OP <= '1';
        WAIT FOR 20 ns;
        -- Reset the system
        reset <= '1';
        WAIT FOR 20 ns;
        reset <= '0';
        WAIT FOR 20 ns;

        -- Test case 3: A + B, OP = '0', ACTIVATION = '1'
        OP <= '0';
        ACTIVATION <= '1';
        WAIT FOR 20 ns;
        -- Reset the system
        reset <= '1';
        WAIT FOR 20 ns;
        reset <= '0';
        WAIT FOR 20 ns;

        -- Test case 4: A * B, OP = '1', ACTIVATION = '1'
        OP <= '1';
        WAIT FOR 20 ns;
        -- Reset the system
        reset <= '1';
        WAIT FOR 20 ns;
        reset <= '0';
        WAIT FOR 20 ns;

        -- End simulation
        WAIT FOR 100 ns;
        WAIT;
    END PROCESS;

END behavior;

tb_syncSignalProcessing.vcd
$date
  Fri Nov  8 17:13:53 2024
$end
$version
  GHDL v0
$end
$timescale
  1 fs
$end
$scope module standard $end
$upscope $end
$scope module std_logic_1164 $end
$upscope $end
$scope module numeric_std $end
$upscope $end
$scope module tb_syncsignalprocessing $end
$var reg 1 ! clk $end
$var reg 1 " reset $end
$var reg 8 # a[7:0] $end
$var reg 8 $ b[7:0] $end
$var reg 1 % activation $end
$var reg 1 & op $end
$var reg 16 ' s[15:0] $end
$scope module uut $end
$var reg 1 ( clk $end
$var reg 1 ) reset $end
$var reg 8 * a[7:0] $end
$var reg 8 + b[7:0] $end
$var reg 1 , activation $end
$var reg 1 - op $end
$var reg 16 . s[15:0] $end
$var reg 8 / sum[7:0] $end
$var reg 16 0 mul[15:0] $end
$var reg 16 1 opout[15:0] $end
$var reg 16 2 activationout[15:0] $end
$var reg 16 3 zero_vector[15:0] $end
$var reg 16 4 sum_resized[15:0] $end
$var reg 16 5 mul_resized[15:0] $end
$scope module u1 $end
$var reg 16 6 a[15:0] $end
$var reg 16 7 b[15:0] $end
$var reg 1 8 sel $end
$var reg 16 9 y[15:0] $end
$upscope $end
$scope module u2 $end
$var reg 16 : a[15:0] $end
$var reg 16 ; b[15:0] $end
$var reg 1 < sel $end
$var reg 16 = y[15:0] $end
$upscope $end
$scope module u3 $end
$var reg 1 > clk $end
$var reg 1 ? reset $end
$var reg 16 @ d[15:0] $end
$var reg 16 A q[15:0] $end
$var reg 16 B reg[15:0] $end
$upscope $end
$upscope $end
$upscope $end
$enddefinitions $end
#0
0!
1"
b00000000 #
b00000000 $
0%
0&
b0000000000000000 '
0(
1)
b00000000 *
b00000000 +
0,
0-
b0000000000000000 .
b00000000 /
b0000000000000000 0
b0000000000000000 1
b0000000000000000 2
b0000000000000000 3
b0000000000000000 4
b0000000000000000 5
b0000000000000000 6
b0000000000000000 7
08
b0000000000000000 9
b0000000000000000 :
b0000000000000000 ;
0<
b0000000000000000 =
0>
1?
b0000000000000000 @
b0000000000000000 A
b0000000000000000 B
#5000000
1!
1(
1>
#10000000
0!
0(
0>
#15000000
1!
1(
1>
#20000000
0!
0"
0(
0)
0>
0?
#25000000
1!
1(
1>
#30000000
0!
0(
0>
#35000000
1!
1(
1>
#40000000
0!
b00001010 #
b00010100 $
0(
b00001010 *
b00010100 +
b00011110 /
b0000000011001000 0
b0000000000011110 1
b0000000000011110 4
b0000000011001000 5
b0000000000011110 6
b0000000011001000 7
b0000000000011110 9
b0000000000011110 ;
0>
#45000000
1!
1(
1>
#50000000
0!
0(
0>
#55000000
1!
1(
1>
#60000000
0!
1"
0(
1)
0>
1?
#65000000
1!
1(
1>
#70000000
0!
0(
0>
#75000000
1!
1(
1>
#80000000
0!
0"
0(
0)
0>
0?
#85000000
1!
1(
1>
#90000000
0!
0(
0>
#95000000
1!
1(
1>
#100000000
0!
1&
0(
1-
b0000000011001000 1
18
b0000000011001000 9
b0000000011001000 ;
0>
#105000000
1!
1(
1>
#110000000
0!
0(
0>
#115000000
1!
1(
1>
#120000000
0!
1"
0(
1)
0>
1?
#125000000
1!
1(
1>
#130000000
0!
0(
0>
#135000000
1!
1(
1>
#140000000
0!
0"
0(
0)
0>
0?
#145000000
1!
1(
1>
#150000000
0!
0(
0>
#155000000
1!
1(
1>
#160000000
0!
1%
0&
0(
1,
0-
b0000000000011110 1
b0000000000011110 2
08
b0000000000011110 9
b0000000000011110 ;
1<
b0000000000011110 =
0>
b0000000000011110 @
#165000000
1!
b0000000000011110 '
1(
b0000000000011110 .
1>
b0000000000011110 A
b0000000000011110 B
#170000000
0!
0(
0>
#175000000
1!
1(
1>
#180000000
0!
1"
b0000000000000000 '
0(
1)
b0000000000000000 .
0>
1?
b0000000000000000 A
b0000000000000000 B
#185000000
1!
1(
1>
#190000000
0!
0(
0>
#195000000
1!
1(
1>
#200000000
0!
0"
0(
0)
0>
0?
#205000000
1!
b0000000000011110 '
1(
b0000000000011110 .
1>
b0000000000011110 A
b0000000000011110 B
#210000000
0!
0(
0>
#215000000
1!
1(
1>
#220000000
0!
1&
0(
1-
b0000000011001000 1
b0000000011001000 2
18
b0000000011001000 9
b0000000011001000 ;
b0000000011001000 =
0>
b0000000011001000 @
#225000000
1!
b0000000011001000 '
1(
b0000000011001000 .
1>
b0000000011001000 A
b0000000011001000 B
#230000000
0!
0(
0>
#235000000
1!
1(
1>
#240000000
0!
1"
b0000000000000000 '
0(
1)
b0000000000000000 .
0>
1?
b0000000000000000 A
b0000000000000000 B
#245000000
1!
1(
1>
#250000000
0!
0(
0>
#255000000
1!
1(
1>
#260000000
0!
0"
0(
0)
0>
0?
#265000000
1!
b0000000011001000 '
1(
b0000000011001000 .
1>
b0000000011001000 A
b0000000011001000 B
